{
    "port": 81,
    "serverID": "41B7B2h7o822S7g4Y0M7u267G2",
    "creationDate": 1727827407286,
    "closes": [],
    "__props__": {
        "id": "G1f7G277p8Z2G704P027w2u9f1",
        "doc": "runningServer203",
        "counter": 203,
        "creationDate": 1727827407291,
        "collection": "runningServer",
        "chunk": "chunk1",
        "lastModified": 1727827407291,
        "dev": false,
        "actions": {},
        "comments": [],
        "collapsed": [],
        "arrange": [],
        "secured": false,
        "size": 366
    }
}