{
    "port": 80,
    "serverID": "D1v7U2U74752q3W8l6P0d2I2o2",
    "creationDate": 1727723860232,
    "closes": [],
    "__props__": {
        "id": "X1m7g2g7N7m2D3V866e0V2g3e6",
        "doc": "runningServer62",
        "counter": 62,
        "creationDate": 1727723860236,
        "collection": "runningServer",
        "chunk": "chunk1",
        "lastModified": 1727723860236,
        "dev": false,
        "actions": {},
        "comments": [],
        "collapsed": [],
        "arrange": [],
        "secured": false,
        "size": 364
    }
}