{
    "port": 85,
    "serverID": "41c7r2B7v920M6b6s0s0j695x0",
    "creationDate": 1727906600659,
    "closes": [],
    "__props__": {
        "id": "M1o7H237Z9z0n6w690l0N6z724",
        "doc": "runningServer471",
        "counter": 471,
        "creationDate": 1727906600674,
        "collection": "runningServer",
        "chunk": "chunk1",
        "lastModified": 1727906600674,
        "dev": false,
        "actions": {},
        "comments": [],
        "collapsed": [],
        "arrange": [],
        "secured": false,
        "size": 366
    }
}