{
    "port": 84,
    "serverID": "M137r2T7B8o2W7E737C3C2q9N7",
    "creationDate": 1727827773309,
    "closes": [],
    "__props__": {
        "id": "81K7d2i7q8p2O7L7v743g3v1R5",
        "doc": "runningServer220",
        "counter": 220,
        "creationDate": 1727827773315,
        "collection": "runningServer",
        "chunk": "chunk1",
        "lastModified": 1727827773315,
        "dev": false,
        "actions": {},
        "comments": [],
        "collapsed": [],
        "arrange": [],
        "secured": false,
        "size": 366
    }
}