{
    "port": 82,
    "serverID": "R1K7W297C9H9O9D2U4t5O4k3B0",
    "creationDate": 1727999245441,
    "closes": [],
    "__props__": {
        "id": "T1Q702Q7l9r9b9H2C4A5n48409",
        "doc": "runningServer579",
        "counter": 579,
        "creationDate": 1727999245449,
        "collection": "runningServer",
        "chunk": "chunk1",
        "lastModified": 1727999245449,
        "dev": false,
        "actions": {},
        "comments": [],
        "collapsed": [],
        "arrange": [],
        "secured": false,
        "size": 366
    }
}