{
    "session": "kN18G7Vh3oy1dR35q35a66a0Gq09759v3Oz8Hx8",
    "user": {
        "firstName": "Mohamad Baker",
        "lastName": "Obeid",
        "agency": {
            "name": "Beirut Group Travel & Tourism",
            "contactBook": {
                "city": "Beirut",
                "country": "Lebanon",
                "contactNumber": "009611234567",
                "address": "Mcharrafiyeh",
                "name": "Beirut Group Travel & Tourism",
                "email": "ceo@beirutgrouptt.com"
            },
            "commissionSheets": [
                {
                    "airline": "Turkish Airlines",
                    "amount": 5,
                    "percentage": true,
                    "releaseDate": 1729424612804,
                    "expiryDate": 1729424603084,
                    "referencePrice": "Gross Fare",
                    "supplier": "supplier1",
                    "name": "Commission Sheet 1",
                    "trips": [
                        "One way",
                        "Round trip"
                    ],
                    "service": "Flight",
                    "age": [
                        "Adult",
                        "Child"
                    ]
                }
            ],
            "permissions": {
                "flight": {
                    "searchByGroup": true
                }
            }
        },
        "contactBook": {
            "city": "Beirut",
            "country": "Lebanon",
            "contactNumber": "009611234567",
            "address": "Mcharrafiyeh",
            "name": "Beirut Group Travel & Tourism",
            "email": "ceo@beirutgrouptt.com"
        }
    },
    "expiryDate": 1731422405388,
    "__props__": {
        "id": "01l7n3r1n3L3i670B0T5L319Z4",
        "doc": "session27",
        "counter": 27,
        "creationDate": 1731336005394,
        "collection": "account.user.session",
        "chunk": "chunk1",
        "lastModified": 1731336005394,
        "dev": true,
        "actions": {},
        "comments": [],
        "collapsed": [],
        "arrange": {},
        "schema": {},
        "secured": false,
        "size": 1169
    }
}