{
    "__props__": {
        "id": "C1O7U2y8U233u9G593K6v5A6J2",
        "doc": "cabin1",
        "counter": 1,
        "creationDate": 1728239536562,
        "collection": "flight.cabin.cabin",
        "chunk": "chunk1",
        "lastModified": 1729811937429,
        "dev": true,
        "actions": {},
        "comments": [],
        "collapsed": [],
        "arrange": {
            "": [
                "cabin",
                "seatCapacity",
                "availabilities"
            ]
        },
        "secured": false,
        "size": 383
    },
    "seatCapacity": 150,
    "availabilities": [
        "availability1"
    ],
    "cabin": "Economy"
}